modlink/__init__.py
modlink/action.py
modlink/agent.py
modlink/context.py
modlink/platform.py
modlink/tools/__init__.py
modlink/tools/action_registry.py
modlink/tools/agent_arg_parser.py
modlink/tools/agent_time.py
modlink-0.1.0a9.dist-info/LICENSE
modlink-0.1.0a9.dist-info/METADATA
modlink-0.1.0a9.dist-info/WHEEL
modlink-0.1.0a9.dist-info/RECORD
