Metadata-Version: 2.3
Name: modlink
Version: 0.1.0a9
Summary: Modular links library for developing agent communication.
License: GPL-3.0-or-later
Author: Kyle Madsen
Author-email: kyle.mdsn@gmail.com
Requires-Python: >=3.10,<4.0
Classifier: License :: OSI Approved :: GNU General Public License v3 or later (GPLv3+)
Classifier: Programming Language :: Python :: 3
Classifier: Programming Language :: Python :: 3.10
Classifier: Programming Language :: Python :: 3.11
Classifier: Programming Language :: Python :: 3.12
Classifier: Programming Language :: Python :: 3.13
Requires-Dist: pydantic (>=2.5.3,<3.0.0)
